LoRa/Const.py
LoRa/LoRa.py
LoRa/__init__.py
LoRathon-1.1.3.dist-info/LICENSE
LoRathon-1.1.3.dist-info/METADATA
LoRathon-1.1.3.dist-info/WHEEL
LoRathon-1.1.3.dist-info/top_level.txt
LoRathon-1.1.3.dist-info/RECORD
