Metadata-Version: 2.1
Name: LoRathon
Version: 1.1.3
Summary: A LoRa commiunication package
Home-page: https://github.com/miladnorouziii/LoRathon
Author: Milad Norouzi
Author-email: miladnorouzi1998@gmail.com
License: GPL-3.0
Keywords: Lora,Lora python,Lora raspberry pi,Lora python library,lora library raspberry pi
Classifier: Development Status :: 3 - Alpha
Classifier: Intended Audience :: Developers
Classifier: License :: OSI Approved :: GNU General Public License (GPL)
Classifier: Programming Language :: Python :: 3
License-File: LICENSE
Requires-Dist: spidev >=1.6
Requires-Dist: RPi.GPIO
